imv_saad/__init__.py
imv_saad/app.py
imv_saad-0.1.0.dist-info/licenses/LICENSE
imv_saad-0.1.0.dist-info/METADATA
imv_saad-0.1.0.dist-info/WHEEL
imv_saad-0.1.0.dist-info/entry_points.txt
imv_saad-0.1.0.dist-info/top_level.txt
imv_saad-0.1.0.dist-info/RECORD
