Metadata-Version: 2.4
Name: imv-saad
Version: 0.1.0
Summary: A Tkinter app for viewing images, masks, predicted masks with overlays and IoU.
Author-email: Saad Wazir <saadwazir.kaist@gmail.com>
License: MIT
Requires-Python: >=3.8
License-File: LICENSE
Requires-Dist: pillow
Requires-Dist: numpy
Dynamic: license-file
